pyrothon/__init__.py
pyrothon/methods.py
pyrothon-0.1.0.dist-info/LICENSE
pyrothon-0.1.0.dist-info/WHEEL
pyrothon-0.1.0.dist-info/METADATA
pyrothon-0.1.0.dist-info/RECORD
